<?xml version="1.0" encoding="UTF-8"?>
<objects serializationModel="Studio.02.02.00">
	<object class="AudioFile" id="{28ae06b3-619a-48fe-bf48-440836f7638a}">
		<property name="assetPath">
			<value>ANIMAL_AFRICAN_WILD_DOG_YELPING04.WAV</value>
		</property>
		<property name="frequencyInKHz">
			<value>48</value>
		</property>
		<property name="channelCount">
			<value>2</value>
		</property>
		<property name="length">
			<value>1.4806666666666699</value>
		</property>
		<relationship name="masterAssetFolder">
			<destination>{13ea243d-7c62-4e4b-a5f2-6631a1d86101}</destination>
		</relationship>
	</object>
</objects>
